Metadata-Version: 1.0
Name: distributions-julio-ml
Version: 1
Summary: Gaussian distributions
Home-page: UNKNOWN
Author: Julio Daniel Pérez Cabrera
Author-email: jdanielperez@outlook.es
License: UNKNOWN
Platform: UNKNOWN
